AUTHORS
CHANGES
LICENSE.txt
MANIFEST.in
README.md
setup.py
stream_framework/__init__.py
stream_framework/activity.py
stream_framework/conftest.py
stream_framework/default_settings.py
stream_framework/exceptions.py
stream_framework/settings.py
stream_framework/tasks.py
stream_framework.egg-info/PKG-INFO
stream_framework.egg-info/SOURCES.txt
stream_framework.egg-info/dependency_links.txt
stream_framework.egg-info/not-zip-safe
stream_framework.egg-info/pbr.json
stream_framework.egg-info/requires.txt
stream_framework.egg-info/top_level.txt
stream_framework/aggregators/__init__.py
stream_framework/aggregators/base.py
stream_framework/feed_managers/__init__.py
stream_framework/feed_managers/base.py
stream_framework/feeds/__init__.py
stream_framework/feeds/base.py
stream_framework/feeds/cassandra.py
stream_framework/feeds/memory.py
stream_framework/feeds/redis.py
stream_framework/feeds/aggregated_feed/__init__.py
stream_framework/feeds/aggregated_feed/base.py
stream_framework/feeds/aggregated_feed/cassandra.py
stream_framework/feeds/aggregated_feed/notification_feed.py
stream_framework/feeds/aggregated_feed/redis.py
stream_framework/feeds/notification_feed/__init__.py
stream_framework/feeds/notification_feed/base.py
stream_framework/feeds/notification_feed/redis.py
stream_framework/metrics/__init__.py
stream_framework/metrics/base.py
stream_framework/metrics/python_statsd.py
stream_framework/metrics/statsd.py
stream_framework/serializers/__init__.py
stream_framework/serializers/activity_serializer.py
stream_framework/serializers/aggregated_activity_serializer.py
stream_framework/serializers/base.py
stream_framework/serializers/dummy.py
stream_framework/serializers/pickle_serializer.py
stream_framework/serializers/simple_timeline_serializer.py
stream_framework/serializers/utils.py
stream_framework/serializers/cassandra/__init__.py
stream_framework/serializers/cassandra/activity_serializer.py
stream_framework/serializers/cassandra/aggregated_activity_serializer.py
stream_framework/storage/__init__.py
stream_framework/storage/base.py
stream_framework/storage/base_lists_storage.py
stream_framework/storage/memory.py
stream_framework/storage/cassandra/__init__.py
stream_framework/storage/cassandra/activity_storage.py
