Metadata-Version: 1.1
Name: stream-framework
Version: 1.3.3
Summary: Stream Framework allows you to build complex feed and caching structures using Redis.
Home-page: https://github.com/tschellenbach/Stream-Framework/
Author: Thierry Schellenbach
Author-email: thierryschellenbach@gmail.com
License: UNKNOWN
Platform: UNKNOWN
Classifier: Intended Audience :: Developers
Classifier: Intended Audience :: System Administrators
Classifier: Operating System :: OS Independent
Classifier: Topic :: Software Development
Classifier: Development Status :: 5 - Production/Stable
Classifier: License :: OSI Approved :: GNU General Public License (GPL)
Classifier: Natural Language :: English
Classifier: Programming Language :: Python
Classifier: Programming Language :: Python :: 2.7
Classifier: Programming Language :: Python :: 3.4
Classifier: Topic :: Scientific/Engineering :: Mathematics
Classifier: Topic :: Software Development :: Libraries :: Python Modules
Classifier: Framework :: Django
